{
  "name": "Effect: Can't Fall Now",
  "type": "effect",
  "effects": [],
  "system": {
    "_migration": {
      "version": 0.954,
      "previous": null
    },
    "description": {
      "value": "<p>Granted by @UUID[Compendium.pf2e-adventures-in-etheirys.feats.Item.lrABBI7IkeYJyzE0]{Can't Fall Now}</p><p>The ally gains a number of temporary Hit Points equal to your level that last for 1 minute.</p>",
      "gm": ""
    },
    "publication": {
      "title": "",
      "authors": "",
      "license": "OGL",
      "remaster": false
    },
    "rules": [
      {
        "key": "TempHP",
        "value": "@item.origin.level"
      }
    ],
    "slug": "effect-cant-fall-now",
    "traits": {
      "otherTags": [],
      "value": []
    },
    "level": {
      "value": 13
    },
    "duration": {
      "value": 1,
      "unit": "minutes",
      "expiry": "turn-end",
      "sustained": false
    },
    "tokenIcon": {
      "show": true
    },
    "unidentified": false,
    "start": {
      "value": 0,
      "initiative": null
    },
    "badge": null,
    "fromSpell": false,
    "context": null
  },
  "img": "icons/magic/defensive/barrier-shield-dome-pink.webp",
  "folder": "vnkS2EMfnbBLoJzZ",
  "flags": {},
  "_stats": {
    "compendiumSource": null,
    "duplicateSource": null,
    "exportSource": null,
    "coreVersion": "13.351",
    "systemId": "pf2e",
    "systemVersion": "7.9.1"
  },
  "ownership": {
    "default": 0,
    "BaYRkOXn1K3wq5i6": 3
  },
  "_id": "sMVII43cS0VyeTpD",
  "sort": 1300000,
  "_key": "!items!sMVII43cS0VyeTpD"
}
