{
  "folder": "4Ki4apN6Wmhy98qs",
  "name": "Blessed Touch",
  "type": "feat",
  "effects": [],
  "system": {
    "_migration": {
      "version": 0.955,
      "previous": {
        "schema": 0.954,
        "foundry": "13.351",
        "system": "7.10.1"
      }
    },
    "description": {
      "value": "<p><strong>Trigger</strong> You use @UUID[Compendium.pf2e-adventures-in-etheirys.actions.Item.K2TXdqQGwIEZcpSf]{Basic Touch}.</p><hr /><p>When you enter your Basic Touch stance, you disperse the magical reinforcement to nearby allies. You grant the extra damage of Basic Touch in an aura affecting all allies in a 5-foot emanation. This uses only the base damage of the stance, based on the ally's weapon specialization; it doesn't use any increase you get from bonuses or the like. As normal for duplicate effects, multiple Basic Touches affecting the same creature aren't cumulative.</p>",
      "gm": ""
    },
    "publication": {
      "title": "",
      "authors": "",
      "license": "OGL",
      "remaster": false
    },
    "rules": [],
    "slug": "blessed-touch",
    "traits": {
      "otherTags": [],
      "value": [
        "disciple"
      ],
      "rarity": "common"
    },
    "level": {
      "value": 16
    },
    "category": "class",
    "onlyLevel1": false,
    "maxTakable": 1,
    "actionType": {
      "value": "free"
    },
    "actions": {
      "value": null
    },
    "prerequisites": {
      "value": [
        {
          "value": "Combat Synthesis"
        }
      ]
    },
    "subfeatures": {
      "proficiencies": {},
      "senses": {},
      "suppressedFeatures": []
    },
    "location": null,
    "selfEffect": {
      "uuid": "Compendium.pf2e-adventures-in-etheirys.feat-effects.Item.PfuDdebTnFuJe76V",
      "name": "Effect: Blessed Touch"
    }
  },
  "img": "icons/sundries/books/book-red-exclamation.webp",
  "flags": {
    "pf2e-toolbelt": {
      "actionable": {}
    }
  },
  "_stats": {
    "compendiumSource": null,
    "duplicateSource": null,
    "exportSource": null,
    "coreVersion": "13.351",
    "systemId": "pf2e",
    "systemVersion": "7.10.1"
  },
  "ownership": {
    "default": 0,
    "BaYRkOXn1K3wq5i6": 3
  },
  "_id": "qr3JzcfppCEFk3CM",
  "sort": 0,
  "_key": "!items!qr3JzcfppCEFk3CM"
}
