{
  "img": "icons/commodities/metal/ingot-hammered-silver.webp",
  "name": "Manifold Alloy",
  "system": {
    "actionType": {
      "value": "passive"
    },
    "actions": {
      "value": null
    },
    "category": "classfeature",
    "description": {
      "value": "<p>You've devised several alloys that contain useful properties of various metals, and you replace a number of parts of your weapon or its ammunition with pieces from these alloys. Your weapon invention is cold iron and silver. This means you deal more damage to a variety of supernatural creatures.</p>",
      "gm": ""
    },
    "level": {
      "value": 7
    },
    "prerequisites": {
      "value": []
    },
    "publication": {
      "license": "ORC",
      "remaster": true,
      "title": "Pathfinder Guns & Gears",
      "authors": ""
    },
    "rules": [
      {
        "definition": [
          "item:id:{actor|flags.pf2e.trackedItems.multiTool}"
        ],
        "key": "AdjustStrike",
        "mode": "add",
        "property": "materials",
        "value": "cold-iron"
      },
      {
        "definition": [
          "item:id:{actor|flags.pf2e.trackedItems.multiTool}"
        ],
        "key": "AdjustStrike",
        "mode": "add",
        "property": "materials",
        "value": "silver"
      }
    ],
    "traits": {
      "otherTags": [
        "skysteel-modification"
      ],
      "rarity": "common",
      "value": [
        "engineer"
      ]
    },
    "slug": "manifold-alloy",
    "_migration": {
      "version": 0.954,
      "previous": null
    },
    "onlyLevel1": false,
    "maxTakable": 1,
    "subfeatures": {
      "proficiencies": {},
      "senses": {},
      "suppressedFeatures": []
    },
    "location": null
  },
  "type": "feat",
  "_stats": {
    "compendiumSource": null,
    "duplicateSource": null,
    "exportSource": null,
    "coreVersion": "13.351",
    "systemId": "pf2e",
    "systemVersion": "7.9.1"
  },
  "effects": [],
  "folder": "vOinOFVoVoyzFsOG",
  "ownership": {
    "default": 0,
    "BaYRkOXn1K3wq5i6": 3
  },
  "flags": {
    "babele": {
      "translated": true,
      "hasTranslation": false,
      "originalName": "Manifold Alloy"
    }
  },
  "_id": "qlfB0ChK6f1jsgPz",
  "sort": 0,
  "_key": "!items!qlfB0ChK6f1jsgPz"
}
