{
  "img": "systems/pf2e/icons/features/classes/razor-prongs.webp",
  "name": "Razor Prongs",
  "system": {
    "actionType": {
      "value": "passive"
    },
    "actions": {
      "value": null
    },
    "category": "classfeature",
    "description": {
      "value": "<p>You can knock down and slash your foes with sharp, curved blades added to your weapon. Your invention gains the tearing (worth <strong>2 TP</strong>), trip, and versatile S traits, and you add the tearing trait to the list of traits you can select for melee multi-tool upgrades.</p>",
      "gm": ""
    },
    "level": {
      "value": 1
    },
    "prerequisites": {
      "value": []
    },
    "publication": {
      "license": "ORC",
      "remaster": true,
      "title": "Pathfinder Guns & Gears",
      "authors": ""
    },
    "rules": [
      {
        "itemId": "{actor|flags.pf2e.trackedItems.multiTool}",
        "key": "ItemAlteration",
        "mode": "add",
        "property": "traits",
        "value": "tearing"
      },
      {
        "itemId": "{actor|flags.pf2e.trackedItems.multiTool}",
        "key": "ItemAlteration",
        "mode": "add",
        "property": "traits",
        "value": "trip"
      },
      {
        "itemId": "{actor|flags.pf2e.trackedItems.multiTool}",
        "key": "ItemAlteration",
        "mode": "add",
        "property": "traits",
        "value": "versatile-s"
      }
    ],
    "traits": {
      "otherTags": [
        "melee",
        "skysteel-modification"
      ],
      "rarity": "common",
      "value": [
        "engineer"
      ]
    },
    "slug": "razor-prongs",
    "_migration": {
      "version": 0.954,
      "previous": null
    },
    "onlyLevel1": false,
    "maxTakable": 1,
    "subfeatures": {
      "proficiencies": {},
      "senses": {},
      "suppressedFeatures": []
    },
    "location": null
  },
  "type": "feat",
  "_stats": {
    "compendiumSource": null,
    "duplicateSource": null,
    "exportSource": null,
    "coreVersion": "13.351",
    "systemId": "pf2e",
    "systemVersion": "7.9.1"
  },
  "effects": [],
  "folder": "wyeI6K5yb8nBTZ8W",
  "ownership": {
    "default": 0,
    "BaYRkOXn1K3wq5i6": 3
  },
  "flags": {
    "babele": {
      "translated": true,
      "hasTranslation": false,
      "originalName": "Razor Prongs"
    }
  },
  "_id": "wckjrxWOkWb5dIG3",
  "sort": 0,
  "_key": "!items!wckjrxWOkWb5dIG3"
}
